setup.py
./cftpl/__init__.py
./cftpl/config.py
./cftpl/run.py
./cftpl/stack.py
./cftpl/template.py
./cftpl/uploader.py
./cftpl/tests/__init__.py
./cftpl/tests/test_config.py
./cftpl/tests/test_run.py
./cftpl/tests/test_stack.py
./cftpl/tests/test_template.py
cftpl.egg-info/PKG-INFO
cftpl.egg-info/SOURCES.txt
cftpl.egg-info/dependency_links.txt
cftpl.egg-info/entry_points.txt
cftpl.egg-info/requires.txt
cftpl.egg-info/top_level.txt