Metadata-Version: 1.1
Name: cftpl
Version: 1.0
Summary: Templates and Management for AWS CloudFormation.
Home-page: https://github.com/hinnerk/cftpl
Author: Hinnerk Haardt, HIT Information-Control GmbH
Author-email: haardt@information-control.de
License: (c) 2014 HIT Information-Control GmbH
Keywords: Amazon Web Services,CloudFormation,AWS
Platform: UNKNOWN
Classifier: Development Status :: 4 - Beta
Classifier: Environment :: Console
Classifier: Intended Audience :: Developers
Classifier: Intended Audience :: Information Technology
Classifier: Intended Audience :: System Administrators
Classifier: License :: OSI Approved :: BSD License
Classifier: Programming Language :: Python :: 2
Classifier: Topic :: System :: Installation/Setup
Classifier: Topic :: System :: Systems Administration
